{
  "1": {
    "name": "略",
    "num": [

    ]
  },
  "2": {
    "name": "略",
    "num": [

    ]
  },
  "3": {
    "name": "略",
    "num": [

    ]
  },
  "4": {
    "name": "略",
    "num": [

    ]
  },
  "5": {
    "name": "略",
    "num": [

    ]
  },
  "6": {
    "name": "略",
    "num": [

    ]
  },
  "7": {
    "name": "略",
    "num": [

    ]
  },
  "8": {
    "name": "略",
    "num": [

    ]
  },
  "9": {
    "name": "略",
    "num": [

    ]
  },
  "10": {
    "name": "略",
    "num": [

    ]
  },
  "11": {
    "name": "略",
    "num": [

    ]
  },
  "12": {
    "name": "略",
    "num": [

    ]
  },
  "13": {
    "name": "略",
    "num": [

    ]
  },
  "14": {
    "name": "略",
    "num": [

    ]
  },
  "15": {
    "name": "略",
    "num": [

    ]
  },
  "16": {
    "name": "略",
    "num": [

    ]
  },
  "17": {
    "name": "略",
    "num": [

    ]
  },
  "18": {
    "name": "略",
    "num": [

    ]
  },
  "19": {
    "name": "略",
    "num": [

    ]
  },
  "20": {
    "name": "略",
    "num": [

    ]
  },
  "21": {
    "name": "略",
    "num": [

    ]
  },
  "22": {
    "name": "略",
    "num": [

    ]
  },
  "23": {
    "name": "略",
    "num": [

    ]
  },
  "24": {
    "name": "略",
    "num": [

    ]
  },
  "25": {
    "name": "略",
    "num": [

    ]
  },
  "26": {
    "name": "略",
    "num": [

    ]
  },
  "27": {
    "name": "略",
    "num": [

    ]
  },
  "28": {
    "name": "略",
    "num": [

    ]
  },
  "29": {
    "name": "略",
    "num": [

    ]
  },
  "30": {
    "name": "略",
    "num": [

    ]
  },
  "31": {
    "name": "略",
    "num": [

    ]
  },
  "32": {
    "name": "略",
    "num": [

    ]
  },
  "33": {
    "name": "略",
    "num": [

    ]
  },
  "34": {
    "name": "略",
    "num": [

    ]
  },
  "35": {
    "name": "略",
    "num": [

    ]
  },
  "36": {
    "name": "略",
    "num": [

    ]
  },
  "37": {
    "name": "略",
    "num": [

    ]
  },
  "38": {
    "name": "略",
    "num": [

    ]
  },
  "39": {
    "name": "略",
    "num": [

    ]
  },
  "40": {
    "name": "略",
    "num": [

    ]
  },
  "41": {
    "name": "略",
    "num": [

    ]
  },
  "42": {
    "name": "略",
    "num": [

    ]
  },
  "43": {
    "name": "略",
    "num": [

    ]
  },
  "44": {
    "name": "略",
    "num": [

    ]
  },
  "45": {
    "name": "略",
    "num": [

    ]
  },
  "46": {
    "name": "略",
    "num": [

    ]
  },
  "47": {
    "name": "略",
    "num": [

    ]
  },
  "48": {
    "name": "略",
    "num": [

    ]
  },
  "49": {
    "name": "略",
    "num": [

    ]
  },
  "50": {
    "name": "略",
    "num": [

    ]
  },
  "51": {
    "name": "略",
    "num": [

    ]
  },
  "52": {
    "name": "略",
    "num": [

    ]
  },
  "53": {
    "name": "略",
    "num": [

    ]
  },
  "54": {
    "name": "略",
    "num": [

    ]
  },
  "55": {
    "name": "略",
    "num": [

    ]
  },
  "56": {
    "name": "略",
    "num": [

    ]
  },
  "57": {
    "name": "略",
    "num": [

    ]
  },
  "58": {
    "name": "略",
    "num": [

    ]
  },
  "59": {
    "name": "略",
    "num": [

    ]
  },
  "60": {
    "name": "略",
    "num": [

    ]
  },
  "61": {
    "name": "略",
    "num": [

    ]
  },
  "62": {
    "name": "略",
    "num": [

    ]
  },
  "63": {
    "name": "略",
    "num": [

    ]
  },
  "64": {
    "name": "略",
    "num": [

    ]
  },
  "65": {
    "name": "略",
    "num": [

    ]
  },
  "66": {
    "name": "略",
    "num": [

    ]
  },
  "67": {
    "name": "略",
    "num": [

    ]
  },
  "68": {
    "name": "略",
    "num": [

    ]
  },
  "69": {
    "name": "略",
    "num": [

    ]
  },
  "70": {
    "name": "略",
    "num": [

    ]
  },
  "71": {
    "name": "略",
    "num": [

    ]
  },
  "72": {
    "name": "略",
    "num": [

    ]
  },
  "73": {
    "name": "略",
    "num": [

    ]
  },
  "74": {
    "name": "略",
    "num": [

    ]
  },
  "75": {
    "name": "略",
    "num": [

    ]
  },
  "76": {
    "name": "略",
    "num": [

    ]
  },
  "77": {
    "name": "略",
    "num": [

    ]
  },
  "78": {
    "name": "略",
    "num": [

    ]
  },
  "79": {
    "name": "略",
    "num": [

    ]
  },
  "80": {
    "name": "略",
    "num": [

    ]
  },
  "81": {
    "name": "略",
    "num": [

    ]
  },
  "82": {
    "name": "略",
    "num": [

    ]
  },
  "83": {
    "name": "略",
    "num": [

    ]
  },
  "84": {
    "name": "略",
    "num": [

    ]
  },
  "85": {
    "name": "略",
    "num": [

    ]
  },
  "86": {
    "name": "略",
    "num": [

    ]
  },
  "87": {
    "name": "略",
    "num": [

    ]
  },
  "88": {
    "name": "略",
    "num": [

    ]
  },
  "89": {
    "name": "略",
    "num": [

    ]
  },
  "90": {
    "name": "略",
    "num": [

    ]
  },
  "91": {
    "name": "略",
    "num": [

    ]
  },
  "92": {
    "name": "略",
    "num": [

    ]
  },
  "93": {
    "name": "略",
    "num": [

    ]
  },
  "94": {
    "name": "略",
    "num": [

    ]
  },
  "95": {
    "name": "略",
    "num": [

    ]
  },
  "96": {
    "name": "略",
    "num": [

    ]
  },
  "97": {
    "name": "略",
    "num": [

    ]
  },
  "98": {
    "name": "略",
    "num": [

    ]
  },
  "99": {
    "name": "略",
    "num": [

    ]
  },
  "100": {
    "name": "略",
    "num": [

    ]
  },
  "101": {
    "name": "略",
    "num": [

    ]
  },
  "102": {
    "name": "略",
    "num": [

    ]
  },
  "103": {
    "name": "略",
    "num": [

    ]
  },
  "104": {
    "name": "略",
    "num": [

    ]
  },
  "105": {
    "name": "略",
    "num": [

    ]
  },
  "106": {
    "name": "略",
    "num": [

    ]
  },
  "107": {
    "name": "略",
    "num": [

    ]
  },
  "108": {
    "name": "略",
    "num": [

    ]
  },
  "109": {
    "name": "略",
    "num": [

    ]
  },
  "110": {
    "name": "略",
    "num": [

    ]
  },
  "111": {
    "name": "略",
    "num": [

    ]
  },
  "112": {
    "name": "略",
    "num": [

    ]
  },
  "113": {
    "name": "略",
    "num": [

    ]
  },
  "114": {
    "name": "略",
    "num": [

    ]
  },
  "115": {
    "name": "略",
    "num": [

    ]
  },
  "116": {
    "name": "略",
    "num": [

    ]
  },
  "117": {
    "name": "略",
    "num": [

    ]
  },
  "118": {
    "name": "略",
    "num": [

    ]
  },
  "119": {
    "name": "略",
    "num": [

    ]
  },
  "120": {
    "name": "略",
    "num": [

    ]
  },
  "121": {
    "name": "略",
    "num": [

    ]
  },
  "122": {
    "name": "略",
    "num": [

    ]
  },
  "123": {
    "name": "略",
    "num": [

    ]
  },
  "124": {
    "name": "略",
    "num": [

    ]
  },
  "125": {
    "name": "略",
    "num": [

    ]
  },
  "126": {
    "name": "略",
    "num": [

    ]
  },
  "127": {
    "name": "略",
    "num": [

    ]
  },
  "128": {
    "name": "略",
    "num": [

    ]
  },
  "129": {
    "name": "略",
    "num": [

    ]
  },
  "130": {
    "name": "略",
    "num": [

    ]
  },
  "131": {
    "name": "略",
    "num": [

    ]
  },
  "132": {
    "name": "略",
    "num": [

    ]
  },
  "133": {
    "name": "略",
    "num": [

    ]
  },
  "134": {
    "name": "略",
    "num": [

    ]
  },
  "135": {
    "name": "略",
    "num": [

    ]
  },
  "136": {
    "name": "略",
    "num": [

    ]
  },
  "137": {
    "name": "略",
    "num": [

    ]
  },
  "138": {
    "name": "略",
    "num": [

    ]
  },
  "139": {
    "name": "略",
    "num": [

    ]
  },
  "140": {
    "name": "略",
    "num": [

    ]
  },
  "141": {
    "name": "略",
    "num": [

    ]
  },
  "142": {
    "name": "略",
    "num": [

    ]
  },
  "143": {
    "name": "略",
    "num": [

    ]
  },
  "144": {
    "name": "略",
    "num": [

    ]
  },
  "145": {
    "name": "略",
    "num": [

    ]
  },
  "146": {
    "name": "略",
    "num": [

    ]
  },
  "147": {
    "name": "略",
    "num": [

    ]
  },
  "148": {
    "name": "略",
    "num": [

    ]
  },
  "149": {
    "name": "略",
    "num": [

    ]
  },
  "150": {
    "name": "略",
    "num": [

    ]
  },
  "151": {
    "name": "略",
    "num": [

    ]
  },
  "152": {
    "name": "略",
    "num": [

    ]
  },
  "153": {
    "name": "略",
    "num": [

    ]
  },
  "154": {
    "name": "略",
    "num": [

    ]
  },
  "155": {
    "name": "略",
    "num": [

    ]
  },
  "156": {
    "name": "略",
    "num": [

    ]
  },
  "157": {
    "name": "略",
    "num": [

    ]
  },
  "158": {
    "name": "略",
    "num": [

    ]
  },
  "159": {
    "name": "略",
    "num": [

    ]
  },
  "160": {
    "name": "略",
    "num": [

    ]
  },
  "161": {
    "name": "略",
    "num": [

    ]
  },
  "162": {
    "name": "略",
    "num": [

    ]
  },
  "163": {
    "name": "略",
    "num": [

    ]
  },
  "164": {
    "name": "略",
    "num": [

    ]
  },
  "165": {
    "name": "略",
    "num": [

    ]
  },
  "166": {
    "name": "略",
    "num": [

    ]
  },
  "167": {
    "name": "略",
    "num": [

    ]
  },
  "168": {
    "name": "略",
    "num": [

    ]
  },
  "169": {
    "name": "略",
    "num": [

    ]
  },
  "170": {
    "name": "略",
    "num": [

    ]
  },
  "171": {
    "name": "略",
    "num": [

    ]
  },
  "172": {
    "name": "略",
    "num": [

    ]
  },
  "173": {
    "name": "略",
    "num": [

    ]
  },
  "174": {
    "name": "略",
    "num": [

    ]
  },
  "175": {
    "name": "略",
    "num": [

    ]
  },
  "176": {
    "name": "略",
    "num": [

    ]
  },
  "177": {
    "name": "略",
    "num": [

    ]
  },
  "178": {
    "name": "略",
    "num": [

    ]
  },
  "179": {
    "name": "略",
    "num": [

    ]
  },
  "180": {
    "name": "旧組合（中央省庁等改革関係法施行法\n（平成十一年法律第百六十号）第千三百二十五条第五項\nに規定する旧組合をいう。次条及び第百八十二条において同じ。）の平成十二年十二月に係る出納計算表及び事業報告書については、なお従前の例による。この場合において、なお従前の例によることとされる第四十八条の規定による改正前の国家公務員共済組合法施行規則\n（以下「改正前国共済施行規則」という。）第六十条第三項\n及び第百十八条第三項\nに規定する大蔵大臣は、財務大臣とする。",
    "num": [

    ]
  },
  "181": {
    "name": "旧組合の平成十二年四月一日に始まる事業年度（次条において「最終事業年度」という。）の終了する月（次項において「解散月」という。）に係る改正前国共済施行規則第五十八条第二項\n、第五十九条第二項並びに第六十条第一項及び第二項の規定の適用については、これらの規定中「毎月末日」とあるのは、「平成十三年一月五日」とする。",
    "num": [

    ]
  },
  "181(2)": {
    "name": "旧組合の解散月に係る帳簿の記入並びに出納計算表及び事業報告書の作成及び提出に係る改正前国共済施行規則第五十八条\nから第六十条\nまで及び第百十八条\nの規定は、なおその効力を有する。この場合において、前項の規定により読み替えられた改正前国共済施行規則第六十条第一項\n中「翌月五日」とあるのは「同月十一日」と、「翌月十五日」とあるのは「同月十九日」と、同条第二項\n中「翌月二十五日」とあるのは「同月末日」と、同条第三項\n中「その提出を受けた月の末日までに、大蔵大臣」とあるのは「平成十三年二月五日までに、財務大臣」と、改正前国共済施行規則第百十八条第一項\n中「毎月末日」とあるのは「平成十三年一月五日」と、「翌月十五日」とあるのは「同月十九日」と、同条第二項\n中「提出を受けた月の二十五日」とあるのは「平成十三年一月末日」と、同条第三項\n中「提出を受けた月の末日までに、大蔵大臣」とあるのは「平成十三年二月五日までに、財務大臣」とする。",
    "num": [

    ]
  },
  "182": {
    "name": "旧組合の最終事業年度の決算に係る改正前国共済施行規則第六十一条\n、第七十八条及び第百十八条の二の規定は、なおその効力を有する。この場合において、改正前国共済施行規則第六十一条第一項\n中「翌事業年度四月十五日」とあるのは「平成十三年一月十九日」と、「翌事業年度四月二十五日」とあるのは「同月末日」と、同条第二項\n中「翌事業年度の五月二十日」とあるのは「平成十三年二月二十三日」と、同条第三項\n中「翌事業年度の五月三十一日までに、大蔵大臣」とあるのは「平成十三年三月六日までに、財務大臣」と、改正前国共済施行規則第七十八条\n中「十二分の二」とあるのは「九分の二」と、改正前国共済施行規則第百十八条の二第一項\n中「翌事業年度の四月二十五日」とあるのは「平成十三年一月末日」と、同条第二項\n中「翌事業年度の五月二十日」とあるのは「平成十三年二月二十三日」と、同条第三項\n中「翌事業年度の五月三十一日までに、大蔵大臣」とあるのは「平成十三年三月六日までに、財務大臣」とする。",
    "num": [

    ]
  },
  "182(2)": {
    "name": "改正前国共済施行規則第八十二条\nの規定により旧組合の最終事業年度の欠損金補てん積立金の額を算定する場合において、同条第一号\nに規定する当該事業年度以前三事業年度における短期給付の平均請求額の算定の基礎となる当該最終事業年度の短期給付の請求額については、当該最終事業年度の短期給付の請求額の九分の十二に相当する額とする。",
    "num": [

    ]
  },
  "183": {
    "name": "新組合（中央省庁等改革関係法施行法第千三百二十八条第一項\nに規定する新組合をいい、防衛庁共済組合（同法第千三百二十四条第一項\nに規定する防衛庁共済組合をいう。）を除く。以下この条において同じ。）の最初の事業年度に係る福祉経理の財源並びに事業計画及び予算の認可については、改正前国共済施行規則第七条第一項\n中「の前事業年度における剰余金」とあるのは「に権利及び義務を承継した旧組合（中央省庁等改革関係法施行法\n（平成十一年法律第百六十号）第千三百二十五条第五項\nに規定する旧組合をいう。）の平成十二年四月一日に始まる事業年度における剰余金」と、改正前国共済施行規則第二十二条\n中「前事業年度の二月末日」とあるのは「平成十二年十一月末日」と読み替えて、これらの規定を適用する。",
    "num": [

    ]
  },
  "183(2)": {
    "name": "新組合の最初の事業年度末日における支払準備金に係る第四十八条の規定による改正後の国家公務員共済組合法施行規則\n（次項及び第百八十五条において「改正後国共済施行規則」という。）第七十八条\nの規定の適用については、同条\n中「十二分の二」とあるのは、「三分の二」とする。",
    "num": [

    ]
  },
  "183(3)": {
    "name": "改正後国共済施行規則第八十二条\nの規定により新組合の最初の事業年度から平成十四年四月一日に始まる事業年度までの各事業年度末日において積み立てるべき欠損金補てん積立金の額を算定する場合において、同条第一号\nに規定する当該事業年度以前三事業年度における短期給付の平均請求額の算定の基礎となる当該最初の事業年度の短期給付の請求額については、当該最初の事業年度の短期給付の請求額の三分の十二に相当する額とする。",
    "num": [

    ]
  },
  "184": {
    "name": "旧総理府共済組合（中央省庁等改革関係法施行法第千三百二十五条第一項\nに規定する旧総理府共済組合をいう。）の組合員であった更新組合員（同法第千三百二十八条第一項\nに規定する更新組合員をいい、同条第七項\nから第九項\nまでの規定によりこの省令の施行の日以後、同法第四百二十三条\nの規定による改正後の国家公務員共済組合法\n（昭和三十三年法律第百二十八号）第百二十四条の二第二項\n、第百二十六条の五第二項又は附則第十二条第三項に規定する継続長期組合員、任意継続組合員又は特例退職組合員となった者を含む。）であって、次の各号に掲げるものに係る組合員原票その他の関係書類（中央省庁等改革関係法施行法第千三百二十五条第一項\nの規定により内閣共済組合（同項\nに規定する内閣共済組合をいう。）に承継される権利及び義務に関する書類を除く。）については、当該各号に定める組合が引き継ぐものとする。",
    "num": [
      "従前の自治省、公正取引委員会及び総務庁に属していた者総務省共済組合（中央省庁等改革関係法施行法第千三百二十三条第項\nに規定する総務省共済組合をいう。）",
      "従前の北海道開発庁及び国土庁に属していた者国土交通省共済組合（中央省庁等改革関係法施行法第千三百十五条第一項\nに規定する国土交通省共済組合をいう。）",
      "従前の科学技術庁に属していた者文部科学省共済組合（中央省庁等改革関係法施行法第千百二十五条第一項\nに規定する文部科学省共済組合をいう。）"
    ]
  },
  "185": {
    "name": "この省令の施行の日において現に交付されている改正前国共済施行規則\n別紙様式第十七号の三\nによる標準負担額減額認定証、別紙様式第三十六号による監査証票及び別紙様式第三十七号による検査証票並びに第百五十三条の規定による改正前の厚生年金保険法\n等の一部を改正する法律等の施行に伴う存続組合及び指定基金に係る特例業務等に関する省令別紙様式第一号\nによる監査証票及び別紙様式第二号\nによる証明書は、当分の間、改正後国共済施行規則\n別紙様式第十七号の三\n、別紙様式第三十六号及び別紙様式第三十七号並びに第百五十三条の規定による改正後の厚生年金保険法\n等の一部を改正する法律等の施行に伴う存続組合及び指定基金に係る特例業務等に関する省令別紙様式第一号\n及び別紙様式第二号\nの様式によるものとみなす。",
    "num": [

    ]
  },
  "186": {
    "name": "次に掲げる省令は、廃止する。",
    "num": [
      "醸造ニ関スル試験、講話其ノ他実地指導申請手続及申請者ノ負担スル旅費歳入納付ニ関スル件（昭和十年大蔵省令第二十号）",
      "大蔵省組織規程（昭和十四年大蔵省令第三十七号）",
      "昭和四十八年度の米生産調整奨励補助金等についての所得税及び法人税の臨時特例に関する法律施行規則（昭和四十九年大蔵省令第六号）",
      "昭和十九年度の稲作転換奨励補助金等についての所得税及び法人税の臨時特例に関する法律施行規則（昭和五十年大蔵省令第号）",
      "昭和十年度の稲作転換奨励補助金等についての所得税及び法人税の臨時特例に関する法律施行規則（昭和十一年大蔵省令第四号）",
      "昭和五十一年度の水田総合利用奨励補助金についての所得税及び法人税の臨時特例に関する法律施行規則（昭和五十二年大蔵省令第二号）",
      "昭和五十二年度の水田総合利用奨励補助金についての所得税及び法人税の臨時特例に関する法律施行規則（昭和五十三年大蔵省令第二号）",
      "昭和五十三年度の水田利用再編奨励補助金についての所得税及び法人税の臨時特例に関する法律施行規則（昭和五十四年大蔵省令第三号）",
      "昭和五十四年度の水田利用再編奨励補助金についての所得税及び法人税の臨時特例に関する法律施行規則（昭和五十五年大蔵省令第五号）",
      "昭和五五年度の水田利用再編奨励補助金についての所得税及び法人税の臨時特例に関する法律施行規則（昭和五六年大蔵省令第一号）",
      "昭和五十六年度の水田利用再編奨励補助金についての所得税及び法人税の臨時特例に関する法律施行規則（昭和五十七年大蔵省令第五号）",
      "昭和五十七年度の水田利用再編奨励補助金についての所得税及び法人税の臨時特例に関する法律施行規則（昭和五十八年大蔵省令第四号）",
      "昭和五十八年度の水田利用再編奨励補助金についての所得税及び法人税の臨時特例に関する法律施行規則（昭和五十九年大蔵省令第二号）",
      "昭和五十九年度の水田利用再編奨励補助金についての所得税及び法人税の臨時特例に関する法律施行規則（昭和六十年大蔵省令第四号）",
      "昭和六十年度の水田利用再編奨励補助金についての所得税及び法人税の臨時特例に関する法律施行規則（昭和六十一年大蔵省令第二号）",
      "昭和六十一年度の水田利用再編奨励補助金についての所得税及び法人税の臨時特例に関する法律施行規則（昭和六十二年大蔵省令第六号）",
      "理財局の資金第二課が所掌する特別会計又は法人を定める省令（昭和六十二年大蔵省令第二号）",
      "昭和六十二年度の水田農業確立助成補助金についての所得税及び法人税の臨時特例に関する法律施行規則（昭和六十三年大蔵省令第二号）",
      "昭和六十三年度の水田農業確立助成補助金についての所得税及び法人税の臨時特例に関する法律施行規則（平成元年大蔵省令第十三号）",
      "平成元年度の水田農業確立助成補助金についての所得税及び法人税の臨時特例に関する法律施行規則（平成二年大蔵省令第二号）"
    ]
  }
}