{
  "1": {
    "name": "この政令は、金融商品取引法等の一部を改正する法律（平成二十一年法律第五十八号）の施行の日（平成二十二年四月一日）から施行する。ただし、次の各号に掲げる規定は、当該各号に定める日から施行する。",
    "num": [
      "第十号の規定貸金業の規制等に関する法律等の部を改正する法律（平成十八年法律第百十五号）附則第条第四号に掲げる規定の施行の日又はこの政令の施行の日のいずれか遅い日",
      "第十五号の規定資金決済に関する法律の施行の日又はこの政令の施行の日のいずれか遅い日"
    ]
  },
  "2": {
    "name": "平成二十五年九月二十九日までの間におけるこの政令の適用については、「次に掲げる者」とあるのは、「次に掲げる者及び証券取引法等の一部を改正する法律の施行に伴う関係法律の整備等に関する法律（平成十八年法律第六十六号）第五十七条第二項の規定によりなおその効力を有するものとされる同法第一条の規定による廃止前の抵当証券業の規制等に関する法律（昭和六十二年法律第百十四号）第四十三条の二第一項の規定による指定を受けた者」とする。",
    "num": [

    ]
  }
}