{
  "body": {
    "1": {
      "main": "国民年金及び企業年金等による高齢期における所得の確保を支援するための国民年金法等の一部を改正する法律（以下「平成二十三年年金確保支援法」という。）附則第二条第一項に規定する政令で定める額は、同項の規定により同項に規定する後納保険料（以下「後納保険料」という。）を納付する月（以下この項において「納付対象月」という。）が次の表の上欄に掲げる年度に属する場合において、当該納付対象月に係る国民年金の保険料に相当する額にそれぞれ同表の下欄に定める率を乗じて得た額（この額に十円未満の端数がある場合においては、その端数金額が五円未満であるときは、これを切り捨て、その端数金額が五円以上であるときは、これを十円として計算する。）とする。\n\n\n平成十七年度\n\n〇・〇九六\n\n\n\n\n平成十八年度\n\n〇・〇七七\n\n\n\n\n平成十九年度\n\n〇・〇六一\n\n\n\n\n平成二十年度\n\n〇・〇四七\n\n\n\n\n平成二十一年度\n\n〇・〇三四\n\n\n\n\n平成二十二年度\n\n〇・〇二二\n\n\n\n\n平成二十三年度\n\n〇・〇一三\n\n\n\n\n平成二十四年度\n\n〇・〇〇六",
      "enum": {
      }
    },
    "1(2)": {
      "main": "厚生労働大臣は、後納保険料の納付に係る期間の各月の国民年金の保険料に相当する額に前項に規定する額を加算した額（後納保険料を納付する場合に納付すべき額）を告示するものとする。",
      "enum": {
      }
    },
    "2": {
      "main": "平成二十三年年金確保支援法附則第八項の規定により国民年金法（昭和三十四年法律第百四十一号）第百九条の四第三項、第四項、第六項及び第七項の規定を準用する場合においては、次の表の上欄に掲げる同条の規定中同表の中欄に掲げる字句は、それぞれ同表の下欄に掲げる字句に読み替えるものとする。\n\n\n第百九条の四第三項\n\n前項の規定による求めがあつた場合において必要があると認めるとき、又は機構\n\n機構\n\n\n\n\n第一項各号に掲げる権限\n\n国民年金及び企業年金等による高齢期における所得の確保を支援するための国民年金法等の一部を改正する法律附則第一項の規定による厚生労働大臣の承認の権限（以下この条において「後納承認の権限」という。）\n\n\n\n\nの全部若しくは一部を行う\n\nを行う\n\n\n\n\n若しくは不適当\n\n又は不適当\n\n\n\n\n同項各号に掲げる権限の全部又は一部\n\n後納承認の権限\n\n\n\n\n第百九条の四第四項\n\n第一項各号に掲げる権限の全部若しくは一部\n\n後納承認の権限\n\n\n\n\n又は前項\n\n又は同項\n\n\n\n\nするとき（次項に規定する場合を除く。）\n\nするとき\n\n\n\n\n第百九条の四第六項\n\n第一項各号に掲げる権限の全部若しくは一部\n\n後納承認の権限\n\n\n\n\n又は第三項\n\n又は同項\n\n\n\n\n同項各号に掲げる権限\n\n後納承認の権限\n\n\n\n\n第百九条の四第七項\n\n前各項\n\n第三項、第四項及び前項\n\n\n\n\n第一項各号に掲げる権限\n\n後納承認の権限\n\n\n\n\n同項各号に掲げる権限\n\n後納承認の権限",
      "enum": {
      }
    },
    "3": {
      "main": "平成二十三年年金確保支援法附則第二条第一項の規定により後納保険料の納付の承認を受けようとする国民年金の被保険者又は被保険者であった者は、国民年金後納保険料納付申込書に、国民年金手帳を添えて、これを日本年金機構に提出しなければならない。",
      "enum": {
      }
    },
    "3(2)": {
      "main": "前項に定めるもののほか、後納保険料の納付の手続その他後納保険料の納付について必要な事項は、厚生労働省令で定める。",
      "enum": {
      }
    }
  },
  "title": "国民年金及び企業年金等による高齢期における所得の確保を支援するための国民年金法等の一部を改正する法律の一部の施行に伴う経過措置に関する政令",
  "cont": {
  }
}