{
  "1": {
    "name": "昭和三年十一月行ハルル大礼記念ノ表章トシテ記念章ヲ設ク",
    "num": [

    ]
  },
  "2": {
    "name": "記念章ノ図式左ノ如シ章銀円形、径一寸トス表面ニハ輪廓内中央ニ高御座、其ノ中心ニ金菊御紋、周辺ニ桜橘文様、左右空間ニ雲文ヲ置キ下方ニ万歳ノ文字ヲ識ス裏面ニハ輪廓ニ菊花形、中央ニ旗形、其ノ左右ニ雲文ヲ置キ旗形ノ内ニ大礼記念章、下方ニ昭和三年十一月ノ文字ヲ識ス環銀円形トス綬織地、幅一寸二分、青黄赤白紫色ノ等分トス記念章ハ綬ヲ以テ左肋ニ佩ブ",
    "num": [

    ]
  },
  "3": {
    "name": "記念章ハ左ニ掲グル者ニ之ヲ授与ス",
    "num": [
      "践祚ノ式ニ召サレタル者",
      "即位礼及大嘗祭ノ式ニ召サレタル者",
      "各所在地ニ於テ饗饌ヲ賜リタル者",
      "大礼ノ事務及大礼ニ伴フ要務ニ関与シタル者"
    ]
  },
  "4": {
    "name": "記念章ハ本人ニ限リ終身之ヲ佩用シ子孫ヲシテ之ヲ保存セシム",
    "num": [

    ]
  },
  "5": {
    "name": "記念章ヲ授与セラルベキ者其ノ授与前死亡シタルトキハ之ヲ其ノ家督相続人又ハ戸主ニ交付シテ保存セシム大礼記念章ノ図",
    "num": [

    ]
  }
}