{
  "1": {
    "name": "会計検査院は、内閣に対し独立の地位を有する。",
    "num": [

    ]
  },
  "2": {
    "name": "会計検査院は、三人の検査官を以て構成する検査官会議と事務総局を以てこれを組織する。",
    "num": [

    ]
  },
  "3": {
    "name": "会計検査院の長は、検査官のうちから互選した者について、内閣においてこれを命ずる。",
    "num": [

    ]
  },
  "4": {
    "name": "検査官は、両議院の同意を経て、内閣がこれを任命する。",
    "num": [

    ]
  },
  "○２": {
    "name": "検査官の任期が満了し、又は欠員を生じた場合において、国会が閉会中であるため又は衆議院の解散のために両議院の同意を経ることができないときは、内閣は、前項の規定にかかわらず、両議院の同意を経ないで、検査官を任命することができる。",
    "num": [

    ]
  },
  "○３": {
    "name": "前項の場合においては、任命の後最初に召集される国会において、両議院の承認を求めなければならない。両議院の承認が得られなかつたときは、その検査官は、当然退官する。",
    "num": [

    ]
  },
  "○４": {
    "name": "検査官の任免は、天皇がこれを認証する。",
    "num": [

    ]
  },
  "○５": {
    "name": "検査官の給与は、別に法律で定める。",
    "num": [

    ]
  },
  "5": {
    "name": "検査官の任期は、七年とし、一回に限り再任されることができる。",
    "num": [

    ]
  }
}