{
  "body": {
    "1": {
      "main": "本計画は、平成二十二年度から平成三十一年度までの十箇年間に行う基準点の測量について定めるものとする。",
      "enum": {
      }
    },
    "2": {
      "main": "基準点の測量は、国土調査促進特別措置法\n（昭和三十七年法律第百四十三号）第三条第一項\nに規定する国土調査事業十箇年計画に基づく地籍調査の実施のために緊急に測量を必要とする地域について行うものとする。",
      "enum": {
      }
    },
    "2(2)": {
      "main": "国土調査法施行令\n（昭和二十七年政令第五十九号）第十二条\nに規定する事業が行われる場合に併せ行われる基準点の測量又は特別の必要により行われる基準点の測量は、前項に規定する地域以外の地域について行うことができる。",
      "enum": {
      }
    },
    "3": {
      "main": "国の機関が地籍調査の基礎とするために行う基準点の測量の基準点（補助基準点を除く。）の数は、八千四百点とする。",
      "enum": {
      }
    },
    "3(2)": {
      "main": "国の機関が地籍調査の基礎とするために行う基準点の測量の補助基準点は、基準点（補助基準点を除く。）を補完するために設置するものとする。",
      "enum": {
      }
    }
  },
  "title": "基準点測量基礎計画",
  "cont": {
  }
}